<annotation>
	<folder>train</folder>
	<filename>00018.jpg</filename>
	<path>/root/workspace/img_test/train/00018.jpg</path>
	<source>
		<database>Unknown</database>
	</source>
	<size>
		<width>1798</width>
		<height>1804</height>
		<depth>3</depth>
	</size>
	<segmented>0</segmented>
	<object>
		<name>Pull Handle</name>
		<pose>Unspecified</pose>
		<truncated>0</truncated>
		<difficult>0</difficult>
		<bndbox>
			<xmin>1332</xmin>
			<ymin>412</ymin>
			<xmax>1678</xmax>
			<ymax>1212</ymax>
		</bndbox>
	</object>
	<object>
		<name>Ball Bearing</name>
		<pose>Unspecified</pose>
		<truncated>0</truncated>
		<difficult>0</difficult>
		<bndbox>
			<xmin>1144</xmin>
			<ymin>896</ymin>
			<xmax>1343</xmax>
			<ymax>1086</ymax>
		</bndbox>
	</object>
	<object>
		<name>T Spring Nut</name>
		<pose>Unspecified</pose>
		<truncated>0</truncated>
		<difficult>0</difficult>
		<bndbox>
			<xmin>580</xmin>
			<ymin>845</ymin>
			<xmax>745</xmax>
			<ymax>1060</ymax>
		</bndbox>
	</object>
	<object>
		<name>T Nut Square</name>
		<pose>Unspecified</pose>
		<truncated>0</truncated>
		<difficult>0</difficult>
		<bndbox>
			<xmin>680</xmin>
			<ymin>523</ymin>
			<xmax>848</xmax>
			<ymax>788</ymax>
		</bndbox>
	</object>
	<object>
		<name>Aluminium Extension</name>
		<pose>Unspecified</pose>
		<truncated>0</truncated>
		<difficult>0</difficult>
		<bndbox>
			<xmin>174</xmin>
			<ymin>1126</ymin>
			<xmax>850</xmax>
			<ymax>1788</ymax>
		</bndbox>
	</object>
	<object>
		<name>Multiwinkel</name>
		<pose>Unspecified</pose>
		<truncated>0</truncated>
		<difficult>0</difficult>
		<bndbox>
			<xmin>282</xmin>
			<ymin>59</ymin>
			<xmax>592</xmax>
			<ymax>507</ymax>
		</bndbox>
	</object>
	<object>
		<name>Socket Head Cap Screw</name>
		<pose>Unspecified</pose>
		<truncated>0</truncated>
		<difficult>0</difficult>
		<bndbox>
			<xmin>1135</xmin>
			<ymin>137</ymin>
			<xmax>1350</xmax>
			<ymax>325</ymax>
		</bndbox>
	</object>
	<object>
		<name>Shoulder Socket Head Cap Screw</name>
		<pose>Unspecified</pose>
		<truncated>0</truncated>
		<difficult>0</difficult>
		<bndbox>
			<xmin>747</xmin>
			<ymin>131</ymin>
			<xmax>1107</xmax>
			<ymax>522</ymax>
		</bndbox>
	</object>
	<object>
		<name>Shoulder Socket Head Cap Screw</name>
		<pose>Unspecified</pose>
		<truncated>0</truncated>
		<difficult>0</difficult>
		<bndbox>
			<xmin>1151</xmin>
			<ymin>1374</ymin>
			<xmax>1615</xmax>
			<ymax>1553</ymax>
		</bndbox>
	</object>
</annotation>
