<annotation>
	<folder>train</folder>
	<filename>000292.jpg</filename>
	<path>/root/workspace/img_test/train/000292.jpg</path>
	<source>
		<database>Unknown</database>
	</source>
	<size>
		<width>1800</width>
		<height>1799</height>
		<depth>3</depth>
	</size>
	<segmented>0</segmented>
	<object>
		<name>Multiwinkel</name>
		<pose>Unspecified</pose>
		<truncated>0</truncated>
		<difficult>0</difficult>
		<bndbox>
			<xmin>1354</xmin>
			<ymin>1264</ymin>
			<xmax>1794</xmax>
			<ymax>1656</ymax>
		</bndbox>
	</object>
	<object>
		<name>Socket Head Cap Screw</name>
		<pose>Unspecified</pose>
		<truncated>0</truncated>
		<difficult>0</difficult>
		<bndbox>
			<xmin>1165</xmin>
			<ymin>1260</ymin>
			<xmax>1258</xmax>
			<ymax>1491</ymax>
		</bndbox>
	</object>
	<object>
		<name>Shoulder Socket Head Cap Screw</name>
		<pose>Unspecified</pose>
		<truncated>0</truncated>
		<difficult>0</difficult>
		<bndbox>
			<xmin>387</xmin>
			<ymin>1355</ymin>
			<xmax>792</xmax>
			<ymax>1684</ymax>
		</bndbox>
	</object>
	<object>
		<name>Shoulder Socket Head Cap Screw</name>
		<pose>Unspecified</pose>
		<truncated>0</truncated>
		<difficult>0</difficult>
		<bndbox>
			<xmin>1445</xmin>
			<ymin>215</ymin>
			<xmax>1749</xmax>
			<ymax>631</ymax>
		</bndbox>
	</object>
	<object>
		<name>Ball Bearing</name>
		<pose>Unspecified</pose>
		<truncated>0</truncated>
		<difficult>0</difficult>
		<bndbox>
			<xmin>1512</xmin>
			<ymin>733</ymin>
			<xmax>1711</xmax>
			<ymax>926</ymax>
		</bndbox>
	</object>
	<object>
		<name>T Spring Nut</name>
		<pose>Unspecified</pose>
		<truncated>0</truncated>
		<difficult>0</difficult>
		<bndbox>
			<xmin>1198</xmin>
			<ymin>927</ymin>
			<xmax>1407</xmax>
			<ymax>1066</ymax>
		</bndbox>
	</object>
	<object>
		<name>T Nut Square</name>
		<pose>Unspecified</pose>
		<truncated>0</truncated>
		<difficult>0</difficult>
		<bndbox>
			<xmin>1025</xmin>
			<ymin>356</ymin>
			<xmax>1274</xmax>
			<ymax>596</ymax>
		</bndbox>
	</object>
	<object>
		<name>Aluminium Extension</name>
		<pose>Unspecified</pose>
		<truncated>0</truncated>
		<difficult>0</difficult>
		<bndbox>
			<xmin>9</xmin>
			<ymin>786</ymin>
			<xmax>523</xmax>
			<ymax>1287</ymax>
		</bndbox>
	</object>
	<object>
		<name>Pull Handle</name>
		<pose>Unspecified</pose>
		<truncated>0</truncated>
		<difficult>0</difficult>
		<bndbox>
			<xmin>103</xmin>
			<ymin>202</ymin>
			<xmax>905</xmax>
			<ymax>686</ymax>
		</bndbox>
	</object>
</annotation>
