<annotation>
	<folder>train</folder>
	<filename>000298.jpg</filename>
	<path>/root/workspace/img_test/train/000298.jpg</path>
	<source>
		<database>Unknown</database>
	</source>
	<size>
		<width>1800</width>
		<height>1799</height>
		<depth>3</depth>
	</size>
	<segmented>0</segmented>
	<object>
		<name>Pull Handle</name>
		<pose>Unspecified</pose>
		<truncated>0</truncated>
		<difficult>0</difficult>
		<bndbox>
			<xmin>1067</xmin>
			<ymin>926</ymin>
			<xmax>1751</xmax>
			<ymax>1607</ymax>
		</bndbox>
	</object>
	<object>
		<name>T Nut Square</name>
		<pose>Unspecified</pose>
		<truncated>0</truncated>
		<difficult>0</difficult>
		<bndbox>
			<xmin>1329</xmin>
			<ymin>669</ymin>
			<xmax>1492</xmax>
			<ymax>922</ymax>
		</bndbox>
	</object>
	<object>
		<name>Ball Bearing</name>
		<pose>Unspecified</pose>
		<truncated>0</truncated>
		<difficult>0</difficult>
		<bndbox>
			<xmin>989</xmin>
			<ymin>549</ymin>
			<xmax>1176</xmax>
			<ymax>740</ymax>
		</bndbox>
	</object>
	<object>
		<name>Aluminium Extension</name>
		<pose>Unspecified</pose>
		<truncated>0</truncated>
		<difficult>0</difficult>
		<bndbox>
			<xmin>131</xmin>
			<ymin>204</ymin>
			<xmax>725</xmax>
			<ymax>753</ymax>
		</bndbox>
	</object>
	<object>
		<name>Socket Head Cap Screw</name>
		<pose>Unspecified</pose>
		<truncated>0</truncated>
		<difficult>0</difficult>
		<bndbox>
			<xmin>671</xmin>
			<ymin>804</ymin>
			<xmax>883</xmax>
			<ymax>986</ymax>
		</bndbox>
	</object>
	<object>
		<name>T Spring Nut</name>
		<pose>Unspecified</pose>
		<truncated>0</truncated>
		<difficult>0</difficult>
		<bndbox>
			<xmin>1047</xmin>
			<ymin>1073</ymin>
			<xmax>1162</xmax>
			<ymax>1275</ymax>
		</bndbox>
	</object>
	<object>
		<name>Multiwinkel</name>
		<pose>Unspecified</pose>
		<truncated>0</truncated>
		<difficult>0</difficult>
		<bndbox>
			<xmin>25</xmin>
			<ymin>993</ymin>
			<xmax>636</xmax>
			<ymax>1353</ymax>
		</bndbox>
	</object>
	<object>
		<name>Shoulder Socket Head Cap Screw</name>
		<pose>Unspecified</pose>
		<truncated>0</truncated>
		<difficult>0</difficult>
		<bndbox>
			<xmin>507</xmin>
			<ymin>1164</ymin>
			<xmax>925</xmax>
			<ymax>1447</ymax>
		</bndbox>
	</object>
	<object>
		<name>Shoulder Socket Head Cap Screw</name>
		<pose>Unspecified</pose>
		<truncated>0</truncated>
		<difficult>0</difficult>
		<bndbox>
			<xmin>1269</xmin>
			<ymin>431</ymin>
			<xmax>1714</xmax>
			<ymax>649</ymax>
		</bndbox>
	</object>
</annotation>
