<annotation>
	<folder>train</folder>
	<filename>000334.jpg</filename>
	<path>/root/workspace/img_test/train/000334.jpg</path>
	<source>
		<database>Unknown</database>
	</source>
	<size>
		<width>1798</width>
		<height>1804</height>
		<depth>3</depth>
	</size>
	<segmented>0</segmented>
	<object>
		<name>Socket Head Cap Screw</name>
		<pose>Unspecified</pose>
		<truncated>0</truncated>
		<difficult>0</difficult>
		<bndbox>
			<xmin>1135</xmin>
			<ymin>1377</ymin>
			<xmax>1276</xmax>
			<ymax>1608</ymax>
		</bndbox>
	</object>
	<object>
		<name>Socket Head Cap Screw</name>
		<pose>Unspecified</pose>
		<truncated>0</truncated>
		<difficult>0</difficult>
		<bndbox>
			<xmin>817</xmin>
			<ymin>1456</ymin>
			<xmax>1041</xmax>
			<ymax>1636</ymax>
		</bndbox>
	</object>
	<object>
		<name>Multiwinkel</name>
		<pose>Unspecified</pose>
		<truncated>0</truncated>
		<difficult>0</difficult>
		<bndbox>
			<xmin>276</xmin>
			<ymin>1112</ymin>
			<xmax>888</xmax>
			<ymax>1486</ymax>
		</bndbox>
	</object>
	<object>
		<name>T Nut Square</name>
		<pose>Unspecified</pose>
		<truncated>0</truncated>
		<difficult>0</difficult>
		<bndbox>
			<xmin>525</xmin>
			<ymin>774</ymin>
			<xmax>696</xmax>
			<ymax>1037</ymax>
		</bndbox>
	</object>
	<object>
		<name>Ball Bearing</name>
		<pose>Unspecified</pose>
		<truncated>0</truncated>
		<difficult>0</difficult>
		<bndbox>
			<xmin>915</xmin>
			<ymin>810</ymin>
			<xmax>1111</xmax>
			<ymax>1005</ymax>
		</bndbox>
	</object>
	<object>
		<name>Pull Handle</name>
		<pose>Unspecified</pose>
		<truncated>0</truncated>
		<difficult>0</difficult>
		<bndbox>
			<xmin>1156</xmin>
			<ymin>449</ymin>
			<xmax>1544</xmax>
			<ymax>1242</ymax>
		</bndbox>
	</object>
	<object>
		<name>Shoulder Socket Head Cap Screw</name>
		<pose>Unspecified</pose>
		<truncated>0</truncated>
		<difficult>0</difficult>
		<bndbox>
			<xmin>1004</xmin>
			<ymin>541</ymin>
			<xmax>1356</xmax>
			<ymax>936</ymax>
		</bndbox>
	</object>
	<object>
		<name>Shoulder Socket Head Cap Screw</name>
		<pose>Unspecified</pose>
		<truncated>0</truncated>
		<difficult>0</difficult>
		<bndbox>
			<xmin>789</xmin>
			<ymin>253</ymin>
			<xmax>1180</xmax>
			<ymax>604</ymax>
		</bndbox>
	</object>
	<object>
		<name>Aluminium Extension</name>
		<pose>Unspecified</pose>
		<truncated>0</truncated>
		<difficult>0</difficult>
		<bndbox>
			<xmin>298</xmin>
			<ymin>175</ymin>
			<xmax>730</xmax>
			<ymax>684</ymax>
		</bndbox>
	</object>
</annotation>
