<annotation>
	<folder>train</folder>
	<filename>000347.jpg</filename>
	<path>/root/workspace/img_test1/train/000347.jpg</path>
	<source>
		<database>Unknown</database>
	</source>
	<size>
		<width>1800</width>
		<height>1800</height>
		<depth>3</depth>
	</size>
	<segmented>0</segmented>
	<object>
		<name>Multiwinkel</name>
		<pose>Unspecified</pose>
		<truncated>0</truncated>
		<difficult>0</difficult>
		<bndbox>
			<xmin>982</xmin>
			<ymin>1266</ymin>
			<xmax>1612</xmax>
			<ymax>1674</ymax>
		</bndbox>
	</object>
	<object>
		<name>Socket Head Cap Screw</name>
		<pose>Unspecified</pose>
		<truncated>0</truncated>
		<difficult>0</difficult>
		<bndbox>
			<xmin>754</xmin>
			<ymin>1295</ymin>
			<xmax>959</xmax>
			<ymax>1496</ymax>
		</bndbox>
	</object>
	<object>
		<name>Shoulder Socket Head Cap Screw</name>
		<pose>Unspecified</pose>
		<truncated>0</truncated>
		<difficult>0</difficult>
		<bndbox>
			<xmin>643</xmin>
			<ymin>911</ymin>
			<xmax>1079</xmax>
			<ymax>1258</ymax>
		</bndbox>
	</object>
	<object>
		<name>Shoulder Socket Head Cap Screw</name>
		<pose>Unspecified</pose>
		<truncated>0</truncated>
		<difficult>0</difficult>
		<bndbox>
			<xmin>296</xmin>
			<ymin>462</ymin>
			<xmax>562</xmax>
			<ymax>935</ymax>
		</bndbox>
	</object>
	<object>
		<name>T Nut Square</name>
		<pose>Unspecified</pose>
		<truncated>0</truncated>
		<difficult>0</difficult>
		<bndbox>
			<xmin>1358</xmin>
			<ymin>980</ymin>
			<xmax>1525</xmax>
			<ymax>1243</ymax>
		</bndbox>
	</object>
	<object>
		<name>T Spring Nut</name>
		<pose>Unspecified</pose>
		<truncated>0</truncated>
		<difficult>0</difficult>
		<bndbox>
			<xmin>188</xmin>
			<ymin>1196</ymin>
			<xmax>404</xmax>
			<ymax>1336</ymax>
		</bndbox>
	</object>
	<object>
		<name>Ball Bearing</name>
		<pose>Unspecified</pose>
		<truncated>0</truncated>
		<difficult>0</difficult>
		<bndbox>
			<xmin>133</xmin>
			<ymin>820</ymin>
			<xmax>309</xmax>
			<ymax>988</ymax>
		</bndbox>
	</object>
	<object>
		<name>Pull Handle</name>
		<pose>Unspecified</pose>
		<truncated>0</truncated>
		<difficult>0</difficult>
		<bndbox>
			<xmin>381</xmin>
			<ymin>77</ymin>
			<xmax>977</xmax>
			<ymax>855</ymax>
		</bndbox>
	</object>
	<object>
		<name>Aluminium Extension</name>
		<pose>Unspecified</pose>
		<truncated>0</truncated>
		<difficult>0</difficult>
		<bndbox>
			<xmin>1065</xmin>
			<ymin>45</ymin>
			<xmax>1683</xmax>
			<ymax>727</ymax>
		</bndbox>
	</object>
</annotation>
