<annotation>
	<folder>train</folder>
	<filename>000395.jpg</filename>
	<path>/root/workspace/img_test1/train/000395.jpg</path>
	<source>
		<database>Unknown</database>
	</source>
	<size>
		<width>1800</width>
		<height>1800</height>
		<depth>3</depth>
	</size>
	<segmented>0</segmented>
	<object>
		<name>Multiwinkel</name>
		<pose>Unspecified</pose>
		<truncated>0</truncated>
		<difficult>0</difficult>
		<bndbox>
			<xmin>882</xmin>
			<ymin>712</ymin>
			<xmax>1333</xmax>
			<ymax>1250</ymax>
		</bndbox>
	</object>
	<object>
		<name>Aluminium Extension</name>
		<pose>Unspecified</pose>
		<truncated>0</truncated>
		<difficult>0</difficult>
		<bndbox>
			<xmin>132</xmin>
			<ymin>647</ymin>
			<xmax>797</xmax>
			<ymax>1216</ymax>
		</bndbox>
	</object>
	<object>
		<name>Pull Handle</name>
		<pose>Unspecified</pose>
		<truncated>0</truncated>
		<difficult>0</difficult>
		<bndbox>
			<xmin>86</xmin>
			<ymin>1127</ymin>
			<xmax>870</xmax>
			<ymax>1723</ymax>
		</bndbox>
	</object>
	<object>
		<name>T Nut Square</name>
		<pose>Unspecified</pose>
		<truncated>0</truncated>
		<difficult>0</difficult>
		<bndbox>
			<xmin>724</xmin>
			<ymin>235</ymin>
			<xmax>975</xmax>
			<ymax>481</ymax>
		</bndbox>
	</object>
	<object>
		<name>T Spring Nut</name>
		<pose>Unspecified</pose>
		<truncated>0</truncated>
		<difficult>0</difficult>
		<bndbox>
			<xmin>271</xmin>
			<ymin>70</ymin>
			<xmax>482</xmax>
			<ymax>296</ymax>
		</bndbox>
	</object>
	<object>
		<name>Ball Bearing</name>
		<pose>Unspecified</pose>
		<truncated>0</truncated>
		<difficult>0</difficult>
		<bndbox>
			<xmin>1563</xmin>
			<ymin>649</ymin>
			<xmax>1744</xmax>
			<ymax>823</ymax>
		</bndbox>
	</object>
	<object>
		<name>Socket Head Cap Screw</name>
		<pose>Unspecified</pose>
		<truncated>0</truncated>
		<difficult>0</difficult>
		<bndbox>
			<xmin>1405</xmin>
			<ymin>1042</ymin>
			<xmax>1542</xmax>
			<ymax>1274</ymax>
		</bndbox>
	</object>
	<object>
		<name>Shoulder Socket Head Cap Screw</name>
		<pose>Unspecified</pose>
		<truncated>0</truncated>
		<difficult>0</difficult>
		<bndbox>
			<xmin>1256</xmin>
			<ymin>1345</ymin>
			<xmax>1666</xmax>
			<ymax>1731</ymax>
		</bndbox>
	</object>
	<object>
		<name>Shoulder Socket Head Cap Screw</name>
		<pose>Unspecified</pose>
		<truncated>1</truncated>
		<difficult>0</difficult>
		<bndbox>
			<xmin>1263</xmin>
			<ymin>1</ymin>
			<xmax>1665</xmax>
			<ymax>393</ymax>
		</bndbox>
	</object>
</annotation>
